migrations/0001_initial.py
migrations/0002_table_name.py
migrations/0003_remove_table_name_l4_is_active.py
migrations/__init__.py
gonghao_django_test-0.1.0.dist-info/LICENSE
gonghao_django_test-0.1.0.dist-info/METADATA
gonghao_django_test-0.1.0.dist-info/WHEEL
gonghao_django_test-0.1.0.dist-info/top_level.txt
gonghao_django_test-0.1.0.dist-info/RECORD
